[{"id": "10207", "dateId": "20200308", "confirmedCount": "5", "confirmedIncr": "5", "deadIncr": "0", "deadCount": "0", "curedIncr": "0", "curedCount": "0"}, {"id": "10208", "dateId": "20200309", "confirmedCount": "9", "confirmedIncr": "4", "deadIncr": "0", "deadCount": "0", "curedIncr": "0", "curedCount": "0"}, {"id": "10209", "dateId": "20200310", "confirmedCount": "9", "confirmedIncr": "0", "deadIncr": "0", "deadCount": "0", "curedIncr": "0", "curedCount": "0"}, {"id": "10210", "dateId": "20200311", "confirmedCount": "13", "confirmedIncr": "4", "deadIncr": "0", "deadCount": "0", "curedIncr": "0", "curedCount": "0"}, {"id": "10211", "dateId": "20200312", "confirmedCount": "13", "confirmedIncr": "0", "deadIncr": "0", "deadCount": "0", "curedIncr": "0", "curedCount": "0"}, {"id": "10212", "dateId": "20200313", "confirmedCount": "22", "confirmedIncr": "9", "deadIncr": "0", "deadCount": "0", "curedIncr": "0", "curedCount": "0"}, {"id": "10213", "dateId": "20200314", "confirmedCount": "23", "confirmedIncr": "1", "deadIncr": "0", "deadCount": "0", "curedIncr": "0", "curedCount": "0"}, {"id": "10214", "dateId": "20200315", "confirmedCount": "23", "confirmedIncr": "0", "deadIncr": "0", "deadCount": "0", "curedIncr": "0", "curedCount": "0"}, {"id": "10215", "dateId": "20200316", "confirmedCount": "23", "confirmedIncr": "0", "deadIncr": "0", "deadCount": "0", "curedIncr": "0", "curedCount": "0"}, {"id": "10216", "dateId": "20200317", "confirmedCount": "41", "confirmedIncr": "18", "deadIncr": "0", "deadCount": "0", "curedIncr": "0", "curedCount": "0"}, {"id": "10217", "dateId": "20200318", "confirmedCount": "41", "confirmedIncr": "0", "deadIncr": "0", "deadCount": "0", "curedIncr": "0", "curedCount": "0"}, {"id": "10218", "dateId": "20200319", "confirmedCount": "87", "confirmedIncr": "46", "deadIncr": "1", "deadCount": "1", "curedIncr": "0", "curedCount": "0"}, {"id": "10219", "dateId": "20200320", "confirmedCount": "113", "confirmedIncr": "26", "deadIncr": "1", "deadCount": "2", "curedIncr": "0", "curedCount": "0"}, {"id": "10220", "dateId": "20200321", "confirmedCount": "113", "confirmedIncr": "0", "deadIncr": "0", "deadCount": "2", "curedIncr": "0", "curedCount": "0"}, {"id": "10221", "dateId": "20200322", "confirmedCount": "117", "confirmedIncr": "4", "deadIncr": "0", "deadCount": "2", "curedIncr": "0", "curedCount": "0"}, {"id": "10222", "dateId": "20200323", "confirmedCount": "158", "confirmedIncr": "41", "deadIncr": "0", "deadCount": "2", "curedIncr": "0", "curedCount": "0"}, {"id": "10223", "dateId": "20200324", "confirmedCount": "158", "confirmedIncr": "0", "deadIncr": "0", "deadCount": "2", "curedIncr": "0", "curedCount": "0"}, {"id": "10224", "dateId": "20200325", "confirmedCount": "201", "confirmedIncr": "43", "deadIncr": "0", "deadCount": "2", "curedIncr": "0", "curedCount": "0"}, {"id": "10225", "dateId": "20200326", "confirmedCount": "231", "confirmedIncr": "30", "deadIncr": "0", "deadCount": "2", "curedIncr": "0", "curedCount": "0"}, {"id": "10226", "dateId": "20200327", "confirmedCount": "263", "confirmedIncr": "32", "deadIncr": "0", "deadCount": "2", "curedIncr": "0", "curedCount": "0"}, {"id": "10227", "dateId": "20200328", "confirmedCount": "295", "confirmedIncr": "32", "deadIncr": "0", "deadCount": "2", "curedIncr": "0", "curedCount": "0"}, {"id": "10228", "dateId": "20200329", "confirmedCount": "295", "confirmedIncr": "0", "deadIncr": "0", "deadCount": "2", "curedIncr": "0", "curedCount": "0"}, {"id": "10229", "dateId": "20200330", "confirmedCount": "295", "confirmedIncr": "0", "deadIncr": "0", "deadCount": "2", "curedIncr": "0", "curedCount": "0"}, {"id": "10230", "dateId": "20200331", "confirmedCount": "347", "confirmedIncr": "52", "deadIncr": "0", "deadCount": "2", "curedIncr": "0", "curedCount": "0"}, {"id": "10231", "dateId": "20200401", "confirmedCount": "347", "confirmedIncr": "0", "deadIncr": "0", "deadCount": "2", "curedIncr": "0", "curedCount": "0"}, {"id": "10232", "dateId": "20200402", "confirmedCount": "347", "confirmedIncr": "0", "deadIncr": "0", "deadCount": "2", "curedIncr": "0", "curedCount": "0"}, {"id": "10233", "dateId": "20200403", "confirmedCount": "375", "confirmedIncr": "28", "deadIncr": "0", "deadCount": "2", "curedIncr": "0", "curedCount": "0"}, {"id": "10234", "dateId": "20200404", "confirmedCount": "396", "confirmedIncr": "21", "deadIncr": "0", "deadCount": "2", "curedIncr": "0", "curedCount": "0"}, {"id": "10235", "dateId": "20200405", "confirmedCount": "416", "confirmedIncr": "20", "deadIncr": "0", "deadCount": "2", "curedIncr": "0", "curedCount": "0"}, {"id": "10236", "dateId": "20200406", "confirmedCount": "435", "confirmedIncr": "19", "deadIncr": "0", "deadCount": "2", "curedIncr": "0", "curedCount": "0"}, {"id": "10237", "dateId": "20200407", "confirmedCount": "454", "confirmedIncr": "19", "deadIncr": "0", "deadCount": "2", "curedIncr": "0", "curedCount": "0"}, {"id": "10238", "dateId": "20200408", "confirmedCount": "467", "confirmedIncr": "13", "deadIncr": "0", "deadCount": "2", "curedIncr": "0", "curedCount": "0"}, {"id": "10239", "dateId": "20200409", "confirmedCount": "483", "confirmedIncr": "16", "deadIncr": "0", "deadCount": "2", "curedIncr": "0", "curedCount": "0"}, {"id": "10240", "dateId": "20200410", "confirmedCount": "502", "confirmedIncr": "19", "deadIncr": "1", "deadCount": "3", "curedIncr": "0", "curedCount": "0"}, {"id": "10241", "dateId": "20200411", "confirmedCount": "539", "confirmedIncr": "37", "deadIncr": "0", "deadCount": "3", "curedIncr": "0", "curedCount": "0"}, {"id": "10242", "dateId": "20200412", "confirmedCount": "558", "confirmedIncr": "19", "deadIncr": "0", "deadCount": "3", "curedIncr": "0", "curedCount": "0"}, {"id": "10243", "dateId": "20200413", "confirmedCount": "577", "confirmedIncr": "19", "deadIncr": "0", "deadCount": "3", "curedIncr": "0", "curedCount": "0"}, {"id": "10244", "dateId": "20200414", "confirmedCount": "595", "confirmedIncr": "18", "deadIncr": "0", "deadCount": "3", "curedIncr": "0", "curedCount": "0"}, {"id": "10245", "dateId": "20200415", "confirmedCount": "612", "confirmedIncr": "17", "deadIncr": "0", "deadCount": "3", "curedIncr": "0", "curedCount": "0"}, {"id": "10246", "dateId": "20200416", "confirmedCount": "618", "confirmedIncr": "6", "deadIncr": "0", "deadCount": "3", "curedIncr": "0", "curedCount": "0"}, {"id": "10247", "dateId": "20200417", "confirmedCount": "626", "confirmedIncr": "8", "deadIncr": "1", "deadCount": "4", "curedIncr": "0", "curedCount": "0"}, {"id": "10248", "dateId": "20200418", "confirmedCount": "642", "confirmedIncr": "16", "deadIncr": "0", "deadCount": "4", "curedIncr": "0", "curedCount": "0"}, {"id": "10249", "dateId": "20200419", "confirmedCount": "649", "confirmedIncr": "7", "deadIncr": "0", "deadCount": "4", "curedIncr": "0", "curedCount": "0"}, {"id": "10250", "dateId": "20200420", "confirmedCount": "655", "confirmedIncr": "6", "deadIncr": "0", "deadCount": "4", "curedIncr": "0", "curedCount": "0"}, {"id": "10251", "dateId": "20200421", "confirmedCount": "660", "confirmedIncr": "5", "deadIncr": "1", "deadCount": "5", "curedIncr": "0", "curedCount": "0"}, {"id": "10252", "dateId": "20200422", "confirmedCount": "662", "confirmedIncr": "2", "deadIncr": "1", "deadCount": "6", "curedIncr": "0", "curedCount": "0"}, {"id": "10253", "dateId": "20200423", "confirmedCount": "669", "confirmedIncr": "7", "deadIncr": "0", "deadCount": "6", "curedIncr": "0", "curedCount": "0"}, {"id": "10254", "dateId": "20200424", "confirmedCount": "681", "confirmedIncr": "12", "deadIncr": "0", "deadCount": "6", "curedIncr": "0", "curedCount": "0"}, {"id": "10255", "dateId": "20200425", "confirmedCount": "686", "confirmedIncr": "5", "deadIncr": "0", "deadCount": "6", "curedIncr": "0", "curedCount": "0"}, {"id": "10256", "dateId": "20200426", "confirmedCount": "687", "confirmedIncr": "1", "deadIncr": "0", "deadCount": "6", "curedIncr": "0", "curedCount": "0"}, {"id": "10257", "dateId": "20200427", "confirmedCount": "693", "confirmedIncr": "6", "deadIncr": "0", "deadCount": "6", "curedIncr": "0", "curedCount": "0"}, {"id": "10258", "dateId": "20200428", "confirmedCount": "695", "confirmedIncr": "2", "deadIncr": "0", "deadCount": "6", "curedIncr": "0", "curedCount": "0"}, {"id": "10259", "dateId": "20200429", "confirmedCount": "697", "confirmedIncr": "2", "deadIncr": "0", "deadCount": "6", "curedIncr": "0", "curedCount": "0"}, {"id": "10260", "dateId": "20200430", "confirmedCount": "705", "confirmedIncr": "8", "deadIncr": "0", "deadCount": "6", "curedIncr": "0", "curedCount": "0"}, {"id": "10261", "dateId": "20200501", "confirmedCount": "713", "confirmedIncr": "8", "deadIncr": "0", "deadCount": "6", "curedIncr": "0", "curedCount": "0"}, {"id": "10262", "dateId": "20200502", "confirmedCount": "719", "confirmedIncr": "6", "deadIncr": "0", "deadCount": "6", "curedIncr": "0", "curedCount": "0"}, {"id": "10263", "dateId": "20200503", "confirmedCount": "725", "confirmedIncr": "6", "deadIncr": "0", "deadCount": "6", "curedIncr": "0", "curedCount": "0"}, {"id": "10264", "dateId": "20200504", "confirmedCount": "733", "confirmedIncr": "8", "deadIncr": "0", "deadCount": "6", "curedIncr": "0", "curedCount": "0"}, {"id": "10265", "dateId": "20200505", "confirmedCount": "739", "confirmedIncr": "6", "deadIncr": "0", "deadCount": "6", "curedIncr": "0", "curedCount": "0"}, {"id": "10266", "dateId": "20200506", "confirmedCount": "742", "confirmedIncr": "3", "deadIncr": "0", "deadCount": "6", "curedIncr": "0", "curedCount": "0"}, {"id": "10267", "dateId": "20200507", "confirmedCount": "755", "confirmedIncr": "13", "deadIncr": "0", "deadCount": "6", "curedIncr": "0", "curedCount": "0"}, {"id": "10268", "dateId": "20200508", "confirmedCount": "761", "confirmedIncr": "6", "deadIncr": "0", "deadCount": "6", "curedIncr": "0", "curedCount": "0"}, {"id": "10269", "dateId": "20200509", "confirmedCount": "765", "confirmedIncr": "4", "deadIncr": "0", "deadCount": "6", "curedIncr": "0", "curedCount": "0"}, {"id": "10270", "dateId": "20200510", "confirmedCount": "773", "confirmedIncr": "8", "deadIncr": "0", "deadCount": "6", "curedIncr": "0", "curedCount": "0"}, {"id": "10271", "dateId": "20200511", "confirmedCount": "780", "confirmedIncr": "7", "deadIncr": "0", "deadCount": "6", "curedIncr": "0", "curedCount": "0"}, {"id": "10272", "dateId": "20200512", "confirmedCount": "792", "confirmedIncr": "12", "deadIncr": "0", "deadCount": "6", "curedIncr": "0", "curedCount": "0"}, {"id": "10273", "dateId": "20200513", "confirmedCount": "801", "confirmedIncr": "9", "deadIncr": "1", "deadCount": "7", "curedIncr": "0", "curedCount": "0"}, {"id": "10274", "dateId": "20200514", "confirmedCount": "804", "confirmedIncr": "3", "deadIncr": "0", "deadCount": "7", "curedIncr": "0", "curedCount": "0"}, {"id": "10275", "dateId": "20200515", "confirmedCount": "815", "confirmedIncr": "11", "deadIncr": "0", "deadCount": "7", "curedIncr": "0", "curedCount": "0"}, {"id": "10276", "dateId": "20200516", "confirmedCount": "830", "confirmedIncr": "15", "deadIncr": "1", "deadCount": "8", "curedIncr": "0", "curedCount": "0"}, {"id": "10277", "dateId": "20200517", "confirmedCount": "843", "confirmedIncr": "13", "deadIncr": "0", "deadCount": "8", "curedIncr": "0", "curedCount": "0"}, {"id": "10278", "dateId": "20200518", "confirmedCount": "853", "confirmedIncr": "10", "deadIncr": "2", "deadCount": "10", "curedIncr": "0", "curedCount": "0"}, {"id": "10279", "dateId": "20200519", "confirmedCount": "863", "confirmedIncr": "10", "deadIncr": "0", "deadCount": "10", "curedIncr": "0", "curedCount": "0"}, {"id": "10280", "dateId": "20200520", "confirmedCount": "882", "confirmedIncr": "19", "deadIncr": "0", "deadCount": "10", "curedIncr": "0", "curedCount": "0"}, {"id": "10281", "dateId": "20200521", "confirmedCount": "882", "confirmedIncr": "0", "deadIncr": "0", "deadCount": "10", "curedIncr": "0", "curedCount": "0"}, {"id": "10282", "dateId": "20200522", "confirmedCount": "882", "confirmedIncr": "0", "deadIncr": "0", "deadCount": "10", "curedIncr": "0", "curedCount": "0"}, {"id": "10283", "dateId": "20200523", "confirmedCount": "903", "confirmedIncr": "21", "deadIncr": "0", "deadCount": "10", "curedIncr": "0", "curedCount": "0"}, {"id": "10284", "dateId": "20200524", "confirmedCount": "911", "confirmedIncr": "8", "deadIncr": "0", "deadCount": "10", "curedIncr": "0", "curedCount": "0"}, {"id": "10285", "dateId": "20200525", "confirmedCount": "918", "confirmedIncr": "7", "deadIncr": "0", "deadCount": "10", "curedIncr": "0", "curedCount": "0"}, {"id": "10286", "dateId": "20200526", "confirmedCount": "930", "confirmedIncr": "12", "deadIncr": "0", "deadCount": "10", "curedIncr": "0", "curedCount": "0"}, {"id": "10287", "dateId": "20200527", "confirmedCount": "951", "confirmedIncr": "21", "deadIncr": "0", "deadCount": "10", "curedIncr": "0", "curedCount": "0"}, {"id": "10288", "dateId": "20200528", "confirmedCount": "956", "confirmedIncr": "5", "deadIncr": "0", "deadCount": "10", "curedIncr": "0", "curedCount": "0"}, {"id": "10289", "dateId": "20200529", "confirmedCount": "984", "confirmedIncr": "28", "deadIncr": "0", "deadCount": "10", "curedIncr": "0", "curedCount": "0"}, {"id": "10290", "dateId": "20200530", "confirmedCount": "1000", "confirmedIncr": "16", "deadIncr": "0", "deadCount": "10", "curedIncr": "0", "curedCount": "0"}, {"id": "10291", "dateId": "20200531", "confirmedCount": "1022", "confirmedIncr": "22", "deadIncr": "0", "deadCount": "10", "curedIncr": "0", "curedCount": "0"}, {"id": "10292", "dateId": "20200601", "confirmedCount": "1047", "confirmedIncr": "25", "deadIncr": "0", "deadCount": "10", "curedIncr": "0", "curedCount": "0"}, {"id": "10293", "dateId": "20200602", "confirmedCount": "1056", "confirmedIncr": "9", "deadIncr": "0", "deadCount": "10", "curedIncr": "0", "curedCount": "0"}, {"id": "10294", "dateId": "20200603", "confirmedCount": "1084", "confirmedIncr": "28", "deadIncr": "0", "deadCount": "10", "curedIncr": "0", "curedCount": "0"}, {"id": "10295", "dateId": "20200604", "confirmedCount": "1105", "confirmedIncr": "21", "deadIncr": "0", "deadCount": "10", "curedIncr": "0", "curedCount": "0"}, {"id": "10296", "dateId": "20200605", "confirmedCount": "1157", "confirmedIncr": "52", "deadIncr": "0", "deadCount": "10", "curedIncr": "0", "curedCount": "0"}, {"id": "10297", "dateId": "20200606", "confirmedCount": "1194", "confirmedIncr": "37", "deadIncr": "0", "deadCount": "10", "curedIncr": "0", "curedCount": "0"}, {"id": "10298", "dateId": "20200607", "confirmedCount": "1263", "confirmedIncr": "69", "deadIncr": "0", "deadCount": "10", "curedIncr": "0", "curedCount": "0"}, {"id": "10299", "dateId": "20200608", "confirmedCount": "1263", "confirmedIncr": "0", "deadIncr": "0", "deadCount": "10", "curedIncr": "0", "curedCount": "0"}, {"id": "10300", "dateId": "20200609", "confirmedCount": "1318", "confirmedIncr": "55", "deadIncr": "0", "deadCount": "10", "curedIncr": "0", "curedCount": "0"}, {"id": "10301", "dateId": "20200610", "confirmedCount": "1342", "confirmedIncr": "24", "deadIncr": "0", "deadCount": "10", "curedIncr": "0", "curedCount": "0"}, {"id": "10302", "dateId": "20200611", "confirmedCount": "1375", "confirmedIncr": "33", "deadIncr": "2", "deadCount": "12", "curedIncr": "0", "curedCount": "0"}, {"id": "10303", "dateId": "20200612", "confirmedCount": "1461", "confirmedIncr": "86", "deadIncr": "0", "deadCount": "12", "curedIncr": "0", "curedCount": "0"}, {"id": "10304", "dateId": "20200613", "confirmedCount": "1538", "confirmedIncr": "77", "deadIncr": "0", "deadCount": "12", "curedIncr": "0", "curedCount": "0"}, {"id": "10305", "dateId": "20200614", "confirmedCount": "1612", "confirmedIncr": "74", "deadIncr": "0", "deadCount": "12", "curedIncr": "0", "curedCount": "0"}, {"id": "10306", "dateId": "20200615", "confirmedCount": "1662", "confirmedIncr": "50", "deadIncr": "0", "deadCount": "12", "curedIncr": "0", "curedCount": "0"}, {"id": "10307", "dateId": "20200616", "confirmedCount": "1715", "confirmedIncr": "53", "deadIncr": "0", "deadCount": "12", "curedIncr": "0", "curedCount": "0"}, {"id": "10308", "dateId": "20200617", "confirmedCount": "1715", "confirmedIncr": "0", "deadIncr": "0", "deadCount": "12", "curedIncr": "0", "curedCount": "0"}, {"id": "10309", "dateId": "20200618", "confirmedCount": "1796", "confirmedIncr": "81", "deadIncr": "0", "deadCount": "12", "curedIncr": "0", "curedCount": "0"}, {"id": "10310", "dateId": "20200619", "confirmedCount": "2058", "confirmedIncr": "262", "deadIncr": "0", "deadCount": "12", "curedIncr": "0", "curedCount": "0"}, {"id": "10311", "dateId": "20200620", "confirmedCount": "2058", "confirmedIncr": "0", "deadIncr": "0", "deadCount": "12", "curedIncr": "0", "curedCount": "0"}, {"id": "10312", "dateId": "20200621", "confirmedCount": "2058", "confirmedIncr": "0", "deadIncr": "0", "deadCount": "12", "curedIncr": "0", "curedCount": "0"}, {"id": "10313", "dateId": "20200622", "confirmedCount": "2127", "confirmedIncr": "69", "deadIncr": "0", "deadCount": "12", "curedIncr": "0", "curedCount": "0"}, {"id": "10314", "dateId": "20200623", "confirmedCount": "2213", "confirmedIncr": "86", "deadIncr": "0", "deadCount": "12", "curedIncr": "0", "curedCount": "0"}, {"id": "10315", "dateId": "20200624", "confirmedCount": "2515", "confirmedIncr": "302", "deadIncr": "0", "deadCount": "12", "curedIncr": "0", "curedCount": "0"}, {"id": "10316", "dateId": "20200625", "confirmedCount": "2515", "confirmedIncr": "0", "deadIncr": "0", "deadCount": "12", "curedIncr": "0", "curedCount": "0"}, {"id": "10317", "dateId": "20200626", "confirmedCount": "2515", "confirmedIncr": "0", "deadIncr": "0", "deadCount": "12", "curedIncr": "0", "curedCount": "0"}, {"id": "10318", "dateId": "20200627", "confirmedCount": "2684", "confirmedIncr": "169", "deadIncr": "0", "deadCount": "12", "curedIncr": "0", "curedCount": "0"}, {"id": "10319", "dateId": "20200628", "confirmedCount": "2836", "confirmedIncr": "152", "deadIncr": "0", "deadCount": "12", "curedIncr": "1280", "curedCount": "1280"}, {"id": "10320", "dateId": "20200629", "confirmedCount": "2979", "confirmedIncr": "143", "deadIncr": "1", "deadCount": "13", "curedIncr": "0", "curedCount": "1280"}, {"id": "10321", "dateId": "20200630", "confirmedCount": "3130", "confirmedIncr": "151", "deadIncr": "2", "deadCount": "15", "curedIncr": "0", "curedCount": "1280"}, {"id": "10322", "dateId": "20200701", "confirmedCount": "3269", "confirmedIncr": "139", "deadIncr": "0", "deadCount": "15", "curedIncr": "0", "curedCount": "1280"}, {"id": "10323", "dateId": "20200702", "confirmedCount": "3459", "confirmedIncr": "190", "deadIncr": "1", "deadCount": "16", "curedIncr": "0", "curedCount": "1280"}]