[{"id": "6315", "dateId": "20200316", "confirmedCount": "3", "confirmedIncr": "3", "deadIncr": "0", "deadCount": "0", "curedIncr": "0", "curedCount": "0"}, {"id": "6316", "dateId": "20200317", "confirmedCount": "3", "confirmedIncr": "0", "deadIncr": "0", "deadCount": "0", "curedIncr": "0", "curedCount": "0"}, {"id": "6317", "dateId": "20200318", "confirmedCount": "3", "confirmedIncr": "0", "deadIncr": "0", "deadCount": "0", "curedIncr": "0", "curedCount": "0"}, {"id": "6318", "dateId": "20200319", "confirmedCount": "5", "confirmedIncr": "2", "deadIncr": "0", "deadCount": "0", "curedIncr": "0", "curedCount": "0"}, {"id": "6319", "dateId": "20200320", "confirmedCount": "6", "confirmedIncr": "1", "deadIncr": "0", "deadCount": "0", "curedIncr": "0", "curedCount": "0"}, {"id": "6320", "dateId": "20200321", "confirmedCount": "14", "confirmedIncr": "8", "deadIncr": "0", "deadCount": "0", "curedIncr": "0", "curedCount": "0"}, {"id": "6321", "dateId": "20200322", "confirmedCount": "21", "confirmedIncr": "7", "deadIncr": "1", "deadCount": "1", "curedIncr": "0", "curedCount": "0"}, {"id": "6322", "dateId": "20200323", "confirmedCount": "23", "confirmedIncr": "2", "deadIncr": "0", "deadCount": "1", "curedIncr": "0", "curedCount": "0"}, {"id": "6323", "dateId": "20200324", "confirmedCount": "31", "confirmedIncr": "8", "deadIncr": "1", "deadCount": "2", "curedIncr": "0", "curedCount": "0"}, {"id": "6324", "dateId": "20200325", "confirmedCount": "39", "confirmedIncr": "8", "deadIncr": "0", "deadCount": "2", "curedIncr": "0", "curedCount": "0"}, {"id": "6325", "dateId": "20200326", "confirmedCount": "51", "confirmedIncr": "12", "deadIncr": "0", "deadCount": "2", "curedIncr": "0", "curedCount": "0"}, {"id": "6326", "dateId": "20200327", "confirmedCount": "64", "confirmedIncr": "13", "deadIncr": "0", "deadCount": "2", "curedIncr": "0", "curedCount": "0"}, {"id": "6327", "dateId": "20200328", "confirmedCount": "64", "confirmedIncr": "0", "deadIncr": "0", "deadCount": "2", "curedIncr": "0", "curedCount": "0"}, {"id": "6328", "dateId": "20200329", "confirmedCount": "64", "confirmedIncr": "0", "deadIncr": "0", "deadCount": "2", "curedIncr": "0", "curedCount": "0"}, {"id": "6329", "dateId": "20200330", "confirmedCount": "64", "confirmedIncr": "0", "deadIncr": "0", "deadCount": "2", "curedIncr": "0", "curedCount": "0"}, {"id": "6330", "dateId": "20200331", "confirmedCount": "174", "confirmedIncr": "110", "deadIncr": "4", "deadCount": "6", "curedIncr": "0", "curedCount": "0"}, {"id": "6331", "dateId": "20200401", "confirmedCount": "239", "confirmedIncr": "65", "deadIncr": "2", "deadCount": "8", "curedIncr": "0", "curedCount": "0"}, {"id": "6332", "dateId": "20200402", "confirmedCount": "286", "confirmedIncr": "47", "deadIncr": "3", "deadCount": "11", "curedIncr": "0", "curedCount": "0"}, {"id": "6333", "dateId": "20200403", "confirmedCount": "316", "confirmedIncr": "30", "deadIncr": "1", "deadCount": "12", "curedIncr": "0", "curedCount": "0"}, {"id": "6334", "dateId": "20200404", "confirmedCount": "378", "confirmedIncr": "62", "deadIncr": "3", "deadCount": "15", "curedIncr": "0", "curedCount": "0"}, {"id": "6335", "dateId": "20200405", "confirmedCount": "452", "confirmedIncr": "74", "deadIncr": "3", "deadCount": "18", "curedIncr": "0", "curedCount": "0"}, {"id": "6336", "dateId": "20200406", "confirmedCount": "452", "confirmedIncr": "0", "deadIncr": "0", "deadCount": "18", "curedIncr": "0", "curedCount": "0"}, {"id": "6337", "dateId": "20200407", "confirmedCount": "513", "confirmedIncr": "61", "deadIncr": "3", "deadCount": "21", "curedIncr": "0", "curedCount": "0"}, {"id": "6338", "dateId": "20200408", "confirmedCount": "573", "confirmedIncr": "60", "deadIncr": "2", "deadCount": "23", "curedIncr": "0", "curedCount": "0"}, {"id": "6339", "dateId": "20200409", "confirmedCount": "620", "confirmedIncr": "47", "deadIncr": "1", "deadCount": "24", "curedIncr": "0", "curedCount": "0"}, {"id": "6340", "dateId": "20200410", "confirmedCount": "683", "confirmedIncr": "63", "deadIncr": "9", "deadCount": "33", "curedIncr": "0", "curedCount": "0"}, {"id": "6341", "dateId": "20200411", "confirmedCount": "725", "confirmedIncr": "42", "deadIncr": "6", "deadCount": "39", "curedIncr": "0", "curedCount": "0"}, {"id": "6342", "dateId": "20200412", "confirmedCount": "788", "confirmedIncr": "63", "deadIncr": "3", "deadCount": "42", "curedIncr": "0", "curedCount": "0"}, {"id": "6343", "dateId": "20200413", "confirmedCount": "897", "confirmedIncr": "109", "deadIncr": "2", "deadCount": "44", "curedIncr": "0", "curedCount": "0"}, {"id": "6344", "dateId": "20200414", "confirmedCount": "903", "confirmedIncr": "6", "deadIncr": "1", "deadCount": "45", "curedIncr": "0", "curedCount": "0"}, {"id": "6345", "dateId": "20200415", "confirmedCount": "923", "confirmedIncr": "20", "deadIncr": "0", "deadCount": "45", "curedIncr": "0", "curedCount": "0"}, {"id": "6346", "dateId": "20200416", "confirmedCount": "974", "confirmedIncr": "51", "deadIncr": "6", "deadCount": "51", "curedIncr": "0", "curedCount": "0"}, {"id": "6347", "dateId": "20200417", "confirmedCount": "1043", "confirmedIncr": "69", "deadIncr": "5", "deadCount": "56", "curedIncr": "0", "curedCount": "0"}, {"id": "6348", "dateId": "20200418", "confirmedCount": "1068", "confirmedIncr": "25", "deadIncr": "2", "deadCount": "58", "curedIncr": "0", "curedCount": "0"}, {"id": "6349", "dateId": "20200419", "confirmedCount": "1118", "confirmedIncr": "50", "deadIncr": "2", "deadCount": "60", "curedIncr": "0", "curedCount": "0"}, {"id": "6350", "dateId": "20200420", "confirmedCount": "1213", "confirmedIncr": "95", "deadIncr": "2", "deadCount": "62", "curedIncr": "0", "curedCount": "0"}, {"id": "6351", "dateId": "20200421", "confirmedCount": "1252", "confirmedIncr": "39", "deadIncr": "1", "deadCount": "63", "curedIncr": "0", "curedCount": "0"}, {"id": "6352", "dateId": "20200422", "confirmedCount": "1298", "confirmedIncr": "46", "deadIncr": "1", "deadCount": "64", "curedIncr": "0", "curedCount": "0"}, {"id": "6353", "dateId": "20200423", "confirmedCount": "1298", "confirmedIncr": "0", "deadIncr": "0", "deadCount": "64", "curedIncr": "0", "curedCount": "0"}, {"id": "6354", "dateId": "20200424", "confirmedCount": "1416", "confirmedIncr": "118", "deadIncr": "0", "deadCount": "64", "curedIncr": "0", "curedCount": "0"}, {"id": "6355", "dateId": "20200425", "confirmedCount": "1416", "confirmedIncr": "0", "deadIncr": "0", "deadCount": "64", "curedIncr": "0", "curedCount": "0"}, {"id": "6356", "dateId": "20200426", "confirmedCount": "1416", "confirmedIncr": "0", "deadIncr": "13", "deadCount": "77", "curedIncr": "0", "curedCount": "0"}, {"id": "6357", "dateId": "20200427", "confirmedCount": "1416", "confirmedIncr": "0", "deadIncr": "0", "deadCount": "77", "curedIncr": "0", "curedCount": "0"}, {"id": "6358", "dateId": "20200428", "confirmedCount": "1416", "confirmedIncr": "0", "deadIncr": "0", "deadCount": "77", "curedIncr": "0", "curedCount": "0"}, {"id": "6359", "dateId": "20200429", "confirmedCount": "1416", "confirmedIncr": "0", "deadIncr": "0", "deadCount": "77", "curedIncr": "0", "curedCount": "0"}, {"id": "6360", "dateId": "20200430", "confirmedCount": "1433", "confirmedIncr": "17", "deadIncr": "0", "deadCount": "77", "curedIncr": "0", "curedCount": "0"}, {"id": "6361", "dateId": "20200501", "confirmedCount": "1539", "confirmedIncr": "106", "deadIncr": "0", "deadCount": "77", "curedIncr": "0", "curedCount": "0"}, {"id": "6362", "dateId": "20200502", "confirmedCount": "1575", "confirmedIncr": "36", "deadIncr": "0", "deadCount": "77", "curedIncr": "0", "curedCount": "0"}, {"id": "6363", "dateId": "20200503", "confirmedCount": "1757", "confirmedIncr": "182", "deadIncr": "0", "deadCount": "77", "curedIncr": "0", "curedCount": "0"}, {"id": "6364", "dateId": "20200504", "confirmedCount": "1808", "confirmedIncr": "51", "deadIncr": "20", "deadCount": "97", "curedIncr": "0", "curedCount": "0"}, {"id": "6365", "dateId": "20200505", "confirmedCount": "1843", "confirmedIncr": "35", "deadIncr": "0", "deadCount": "97", "curedIncr": "0", "curedCount": "0"}, {"id": "6366", "dateId": "20200506", "confirmedCount": "1924", "confirmedIncr": "81", "deadIncr": "0", "deadCount": "97", "curedIncr": "0", "curedCount": "0"}, {"id": "6367", "dateId": "20200507", "confirmedCount": "1968", "confirmedIncr": "44", "deadIncr": "0", "deadCount": "97", "curedIncr": "0", "curedCount": "0"}, {"id": "6368", "dateId": "20200508", "confirmedCount": "2031", "confirmedIncr": "63", "deadIncr": "0", "deadCount": "97", "curedIncr": "0", "curedCount": "0"}, {"id": "6369", "dateId": "20200509", "confirmedCount": "2156", "confirmedIncr": "125", "deadIncr": "0", "deadCount": "97", "curedIncr": "0", "curedCount": "0"}, {"id": "6370", "dateId": "20200510", "confirmedCount": "2173", "confirmedIncr": "17", "deadIncr": "11", "deadCount": "108", "curedIncr": "0", "curedCount": "0"}, {"id": "6371", "dateId": "20200511", "confirmedCount": "2198", "confirmedIncr": "25", "deadIncr": "3", "deadCount": "111", "curedIncr": "0", "curedCount": "0"}, {"id": "6372", "dateId": "20200512", "confirmedCount": "2256", "confirmedIncr": "58", "deadIncr": "2", "deadCount": "113", "curedIncr": "0", "curedCount": "0"}, {"id": "6373", "dateId": "20200513", "confirmedCount": "2299", "confirmedIncr": "43", "deadIncr": "1", "deadCount": "114", "curedIncr": "0", "curedCount": "0"}, {"id": "6374", "dateId": "20200514", "confirmedCount": "2329", "confirmedIncr": "30", "deadIncr": "1", "deadCount": "115", "curedIncr": "0", "curedCount": "0"}, {"id": "6375", "dateId": "20200515", "confirmedCount": "2427", "confirmedIncr": "98", "deadIncr": "2", "deadCount": "117", "curedIncr": "0", "curedCount": "0"}, {"id": "6376", "dateId": "20200516", "confirmedCount": "2542", "confirmedIncr": "115", "deadIncr": "5", "deadCount": "122", "curedIncr": "0", "curedCount": "0"}, {"id": "6377", "dateId": "20200517", "confirmedCount": "2589", "confirmedIncr": "47", "deadIncr": "0", "deadCount": "122", "curedIncr": "0", "curedCount": "0"}, {"id": "6378", "dateId": "20200518", "confirmedCount": "2646", "confirmedIncr": "57", "deadIncr": "1", "deadCount": "123", "curedIncr": "0", "curedCount": "0"}, {"id": "6379", "dateId": "20200519", "confirmedCount": "2710", "confirmedIncr": "64", "deadIncr": "1", "deadCount": "124", "curedIncr": "0", "curedCount": "0"}, {"id": "6380", "dateId": "20200520", "confirmedCount": "2805", "confirmedIncr": "95", "deadIncr": "0", "deadCount": "124", "curedIncr": "0", "curedCount": "0"}, {"id": "6381", "dateId": "20200521", "confirmedCount": "2866", "confirmedIncr": "61", "deadIncr": "1", "deadCount": "125", "curedIncr": "0", "curedCount": "0"}, {"id": "6382", "dateId": "20200522", "confirmedCount": "2913", "confirmedIncr": "47", "deadIncr": "1", "deadCount": "126", "curedIncr": "0", "curedCount": "0"}, {"id": "6383", "dateId": "20200523", "confirmedCount": "3030", "confirmedIncr": "117", "deadIncr": "0", "deadCount": "126", "curedIncr": "0", "curedCount": "0"}, {"id": "6384", "dateId": "20200524", "confirmedCount": "3100", "confirmedIncr": "70", "deadIncr": "1", "deadCount": "127", "curedIncr": "0", "curedCount": "0"}, {"id": "6385", "dateId": "20200525", "confirmedCount": "3189", "confirmedIncr": "89", "deadIncr": "0", "deadCount": "127", "curedIncr": "0", "curedCount": "0"}, {"id": "6386", "dateId": "20200526", "confirmedCount": "3260", "confirmedIncr": "71", "deadIncr": "2", "deadCount": "129", "curedIncr": "0", "curedCount": "0"}, {"id": "6387", "dateId": "20200527", "confirmedCount": "3324", "confirmedIncr": "64", "deadIncr": "0", "deadCount": "129", "curedIncr": "0", "curedCount": "0"}, {"id": "6388", "dateId": "20200528", "confirmedCount": "3397", "confirmedIncr": "73", "deadIncr": "0", "deadCount": "129", "curedIncr": "0", "curedCount": "0"}, {"id": "6389", "dateId": "20200529", "confirmedCount": "3486", "confirmedIncr": "89", "deadIncr": "2", "deadCount": "131", "curedIncr": "0", "curedCount": "0"}, {"id": "6390", "dateId": "20200530", "confirmedCount": "3647", "confirmedIncr": "161", "deadIncr": "1", "deadCount": "132", "curedIncr": "0", "curedCount": "0"}, {"id": "6391", "dateId": "20200531", "confirmedCount": "3718", "confirmedIncr": "71", "deadIncr": "1", "deadCount": "133", "curedIncr": "0", "curedCount": "0"}, {"id": "6392", "dateId": "20200601", "confirmedCount": "3776", "confirmedIncr": "58", "deadIncr": "3", "deadCount": "136", "curedIncr": "0", "curedCount": "0"}, {"id": "6393", "dateId": "20200602", "confirmedCount": "3873", "confirmedIncr": "97", "deadIncr": "0", "deadCount": "136", "curedIncr": "0", "curedCount": "0"}, {"id": "6394", "dateId": "20200603", "confirmedCount": "3935", "confirmedIncr": "62", "deadIncr": "2", "deadCount": "138", "curedIncr": "0", "curedCount": "0"}, {"id": "6395", "dateId": "20200604", "confirmedCount": "4023", "confirmedIncr": "88", "deadIncr": "2", "deadCount": "140", "curedIncr": "0", "curedCount": "0"}, {"id": "6396", "dateId": "20200605", "confirmedCount": "4508", "confirmedIncr": "485", "deadIncr": "0", "deadCount": "140", "curedIncr": "0", "curedCount": "0"}, {"id": "6397", "dateId": "20200606", "confirmedCount": "4620", "confirmedIncr": "112", "deadIncr": "1", "deadCount": "141", "curedIncr": "0", "curedCount": "0"}, {"id": "6398", "dateId": "20200607", "confirmedCount": "4915", "confirmedIncr": "295", "deadIncr": "1", "deadCount": "142", "curedIncr": "0", "curedCount": "0"}, {"id": "6399", "dateId": "20200608", "confirmedCount": "4985", "confirmedIncr": "70", "deadIncr": "0", "deadCount": "142", "curedIncr": "0", "curedCount": "0"}, {"id": "6400", "dateId": "20200609", "confirmedCount": "5046", "confirmedIncr": "61", "deadIncr": "0", "deadCount": "142", "curedIncr": "0", "curedCount": "0"}, {"id": "6401", "dateId": "20200610", "confirmedCount": "5185", "confirmedIncr": "139", "deadIncr": "0", "deadCount": "142", "curedIncr": "0", "curedCount": "0"}, {"id": "6402", "dateId": "20200611", "confirmedCount": "5329", "confirmedIncr": "144", "deadIncr": "1", "deadCount": "143", "curedIncr": "0", "curedCount": "0"}, {"id": "6403", "dateId": "20200612", "confirmedCount": "5352", "confirmedIncr": "23", "deadIncr": "1", "deadCount": "144", "curedIncr": "0", "curedCount": "0"}, {"id": "6404", "dateId": "20200613", "confirmedCount": "5536", "confirmedIncr": "184", "deadIncr": "2", "deadCount": "146", "curedIncr": "0", "curedCount": "0"}, {"id": "6405", "dateId": "20200614", "confirmedCount": "5690", "confirmedIncr": "154", "deadIncr": "0", "deadCount": "146", "curedIncr": "0", "curedCount": "0"}, {"id": "6406", "dateId": "20200615", "confirmedCount": "5811", "confirmedIncr": "121", "deadIncr": "1", "deadCount": "147", "curedIncr": "0", "curedCount": "0"}, {"id": "6407", "dateId": "20200616", "confirmedCount": "5890", "confirmedIncr": "79", "deadIncr": "0", "deadCount": "147", "curedIncr": "0", "curedCount": "0"}, {"id": "6408", "dateId": "20200617", "confirmedCount": "5890", "confirmedIncr": "0", "deadIncr": "0", "deadCount": "147", "curedIncr": "0", "curedCount": "0"}, {"id": "6409", "dateId": "20200618", "confirmedCount": "6003", "confirmedIncr": "113", "deadIncr": "0", "deadCount": "147", "curedIncr": "0", "curedCount": "0"}, {"id": "6410", "dateId": "20200619", "confirmedCount": "6111", "confirmedIncr": "108", "deadIncr": "0", "deadCount": "147", "curedIncr": "0", "curedCount": "0"}, {"id": "6411", "dateId": "20200620", "confirmedCount": "6195", "confirmedIncr": "84", "deadIncr": "0", "deadCount": "147", "curedIncr": "0", "curedCount": "0"}, {"id": "6412", "dateId": "20200621", "confirmedCount": "6463", "confirmedIncr": "268", "deadIncr": "0", "deadCount": "147", "curedIncr": "0", "curedCount": "0"}, {"id": "6413", "dateId": "20200622", "confirmedCount": "6525", "confirmedIncr": "62", "deadIncr": "2", "deadCount": "149", "curedIncr": "0", "curedCount": "0"}, {"id": "6414", "dateId": "20200623", "confirmedCount": "6564", "confirmedIncr": "39", "deadIncr": "0", "deadCount": "149", "curedIncr": "0", "curedCount": "0"}, {"id": "6415", "dateId": "20200624", "confirmedCount": "6685", "confirmedIncr": "121", "deadIncr": "0", "deadCount": "149", "curedIncr": "0", "curedCount": "0"}, {"id": "6416", "dateId": "20200625", "confirmedCount": "6820", "confirmedIncr": "135", "deadIncr": "0", "deadCount": "149", "curedIncr": "0", "curedCount": "0"}, {"id": "6417", "dateId": "20200626", "confirmedCount": "6877", "confirmedIncr": "57", "deadIncr": "2", "deadCount": "151", "curedIncr": "0", "curedCount": "0"}, {"id": "6418", "dateId": "20200627", "confirmedCount": "6922", "confirmedIncr": "45", "deadIncr": "0", "deadCount": "151", "curedIncr": "0", "curedCount": "0"}, {"id": "6419", "dateId": "20200628", "confirmedCount": "7066", "confirmedIncr": "144", "deadIncr": "1", "deadCount": "152", "curedIncr": "0", "curedCount": "0"}, {"id": "6420", "dateId": "20200629", "confirmedCount": "7189", "confirmedIncr": "123", "deadIncr": "1", "deadCount": "153", "curedIncr": "0", "curedCount": "0"}, {"id": "6421", "dateId": "20200630", "confirmedCount": "7250", "confirmedIncr": "61", "deadIncr": "0", "deadCount": "153", "curedIncr": "0", "curedCount": "0"}, {"id": "6422", "dateId": "20200701", "confirmedCount": "7465", "confirmedIncr": "215", "deadIncr": "0", "deadCount": "153", "curedIncr": "0", "curedCount": "0"}, {"id": "6423", "dateId": "20200702", "confirmedCount": "7537", "confirmedIncr": "72", "deadIncr": "0", "deadCount": "153", "curedIncr": "0", "curedCount": "0"}]