[{"id": "1356", "dateId": "20200201", "confirmedCount": "1", "confirmedIncr": "1", "deadIncr": "0", "deadCount": "0", "curedIncr": "0", "curedCount": "0"}, {"id": "1357", "dateId": "20200202", "confirmedCount": "1", "confirmedIncr": "0", "deadIncr": "0", "deadCount": "0", "curedIncr": "0", "curedCount": "0"}, {"id": "1358", "dateId": "20200203", "confirmedCount": "1", "confirmedIncr": "0", "deadIncr": "0", "deadCount": "0", "curedIncr": "0", "curedCount": "0"}, {"id": "1359", "dateId": "20200204", "confirmedCount": "1", "confirmedIncr": "0", "deadIncr": "0", "deadCount": "0", "curedIncr": "0", "curedCount": "0"}, {"id": "1360", "dateId": "20200205", "confirmedCount": "1", "confirmedIncr": "0", "deadIncr": "0", "deadCount": "0", "curedIncr": "0", "curedCount": "0"}, {"id": "1361", "dateId": "20200206", "confirmedCount": "1", "confirmedIncr": "0", "deadIncr": "0", "deadCount": "0", "curedIncr": "0", "curedCount": "0"}, {"id": "1362", "dateId": "20200207", "confirmedCount": "1", "confirmedIncr": "0", "deadIncr": "0", "deadCount": "0", "curedIncr": "0", "curedCount": "0"}, {"id": "1363", "dateId": "20200208", "confirmedCount": "1", "confirmedIncr": "0", "deadIncr": "0", "deadCount": "0", "curedIncr": "0", "curedCount": "0"}, {"id": "1364", "dateId": "20200209", "confirmedCount": "1", "confirmedIncr": "0", "deadIncr": "0", "deadCount": "0", "curedIncr": "0", "curedCount": "0"}, {"id": "1365", "dateId": "20200210", "confirmedCount": "2", "confirmedIncr": "1", "deadIncr": "0", "deadCount": "0", "curedIncr": "0", "curedCount": "0"}, {"id": "1366", "dateId": "20200211", "confirmedCount": "2", "confirmedIncr": "0", "deadIncr": "0", "deadCount": "0", "curedIncr": "0", "curedCount": "0"}, {"id": "1367", "dateId": "20200212", "confirmedCount": "2", "confirmedIncr": "0", "deadIncr": "0", "deadCount": "0", "curedIncr": "0", "curedCount": "0"}, {"id": "1368", "dateId": "20200213", "confirmedCount": "2", "confirmedIncr": "0", "deadIncr": "0", "deadCount": "0", "curedIncr": "0", "curedCount": "0"}, {"id": "1369", "dateId": "20200214", "confirmedCount": "2", "confirmedIncr": "0", "deadIncr": "0", "deadCount": "0", "curedIncr": "0", "curedCount": "0"}, {"id": "1370", "dateId": "20200215", "confirmedCount": "2", "confirmedIncr": "0", "deadIncr": "0", "deadCount": "0", "curedIncr": "0", "curedCount": "0"}, {"id": "1371", "dateId": "20200216", "confirmedCount": "2", "confirmedIncr": "0", "deadIncr": "0", "deadCount": "0", "curedIncr": "0", "curedCount": "0"}, {"id": "1372", "dateId": "20200217", "confirmedCount": "2", "confirmedIncr": "0", "deadIncr": "0", "deadCount": "0", "curedIncr": "0", "curedCount": "0"}, {"id": "1373", "dateId": "20200218", "confirmedCount": "2", "confirmedIncr": "0", "deadIncr": "0", "deadCount": "0", "curedIncr": "0", "curedCount": "0"}, {"id": "1374", "dateId": "20200219", "confirmedCount": "2", "confirmedIncr": "0", "deadIncr": "0", "deadCount": "0", "curedIncr": "0", "curedCount": "0"}, {"id": "1375", "dateId": "20200220", "confirmedCount": "2", "confirmedIncr": "0", "deadIncr": "0", "deadCount": "0", "curedIncr": "0", "curedCount": "0"}, {"id": "1376", "dateId": "20200221", "confirmedCount": "2", "confirmedIncr": "0", "deadIncr": "0", "deadCount": "0", "curedIncr": "0", "curedCount": "0"}, {"id": "1377", "dateId": "20200222", "confirmedCount": "2", "confirmedIncr": "0", "deadIncr": "0", "deadCount": "0", "curedIncr": "0", "curedCount": "0"}, {"id": "1378", "dateId": "20200223", "confirmedCount": "2", "confirmedIncr": "0", "deadIncr": "0", "deadCount": "0", "curedIncr": "0", "curedCount": "0"}, {"id": "1379", "dateId": "20200224", "confirmedCount": "2", "confirmedIncr": "0", "deadIncr": "0", "deadCount": "0", "curedIncr": "0", "curedCount": "0"}, {"id": "1380", "dateId": "20200225", "confirmedCount": "2", "confirmedIncr": "0", "deadIncr": "0", "deadCount": "0", "curedIncr": "0", "curedCount": "0"}, {"id": "1381", "dateId": "20200226", "confirmedCount": "2", "confirmedIncr": "0", "deadIncr": "0", "deadCount": "0", "curedIncr": "0", "curedCount": "0"}, {"id": "1382", "dateId": "20200227", "confirmedCount": "12", "confirmedIncr": "10", "deadIncr": "0", "deadCount": "0", "curedIncr": "0", "curedCount": "0"}, {"id": "1383", "dateId": "20200228", "confirmedCount": "25", "confirmedIncr": "13", "deadIncr": "0", "deadCount": "0", "curedIncr": "0", "curedCount": "0"}, {"id": "1384", "dateId": "20200229", "confirmedCount": "32", "confirmedIncr": "7", "deadIncr": "0", "deadCount": "0", "curedIncr": "0", "curedCount": "0"}, {"id": "1385", "dateId": "20200301", "confirmedCount": "45", "confirmedIncr": "13", "deadIncr": "0", "deadCount": "0", "curedIncr": "0", "curedCount": "0"}, {"id": "1386", "dateId": "20200302", "confirmedCount": "45", "confirmedIncr": "0", "deadIncr": "0", "deadCount": "0", "curedIncr": "0", "curedCount": "0"}, {"id": "1387", "dateId": "20200303", "confirmedCount": "114", "confirmedIncr": "69", "deadIncr": "0", "deadCount": "0", "curedIncr": "0", "curedCount": "0"}, {"id": "1388", "dateId": "20200304", "confirmedCount": "151", "confirmedIncr": "37", "deadIncr": "0", "deadCount": "0", "curedIncr": "0", "curedCount": "0"}, {"id": "1389", "dateId": "20200305", "confirmedCount": "198", "confirmedIncr": "47", "deadIncr": "1", "deadCount": "1", "curedIncr": "0", "curedCount": "0"}, {"id": "1390", "dateId": "20200306", "confirmedCount": "257", "confirmedIncr": "59", "deadIncr": "2", "deadCount": "3", "curedIncr": "0", "curedCount": "0"}, {"id": "1391", "dateId": "20200307", "confirmedCount": "374", "confirmedIncr": "117", "deadIncr": "2", "deadCount": "5", "curedIncr": "0", "curedCount": "0"}, {"id": "1392", "dateId": "20200308", "confirmedCount": "430", "confirmedIncr": "56", "deadIncr": "0", "deadCount": "5", "curedIncr": "0", "curedCount": "0"}, {"id": "1393", "dateId": "20200309", "confirmedCount": "589", "confirmedIncr": "159", "deadIncr": "5", "deadCount": "10", "curedIncr": "0", "curedCount": "0"}, {"id": "1394", "dateId": "20200310", "confirmedCount": "1024", "confirmedIncr": "435", "deadIncr": "18", "deadCount": "28", "curedIncr": "0", "curedCount": "0"}, {"id": "1395", "dateId": "20200311", "confirmedCount": "1639", "confirmedIncr": "615", "deadIncr": "8", "deadCount": "36", "curedIncr": "0", "curedCount": "0"}, {"id": "1396", "dateId": "20200312", "confirmedCount": "2140", "confirmedIncr": "501", "deadIncr": "12", "deadCount": "48", "curedIncr": "0", "curedCount": "0"}, {"id": "1397", "dateId": "20200313", "confirmedCount": "2965", "confirmedIncr": "825", "deadIncr": "36", "deadCount": "84", "curedIncr": "0", "curedCount": "0"}, {"id": "1398", "dateId": "20200314", "confirmedCount": "4231", "confirmedIncr": "1266", "deadIncr": "36", "deadCount": "120", "curedIncr": "0", "curedCount": "0"}, {"id": "1399", "dateId": "20200315", "confirmedCount": "5753", "confirmedIncr": "1522", "deadIncr": "16", "deadCount": "136", "curedIncr": "571", "curedCount": "571"}, {"id": "1400", "dateId": "20200316", "confirmedCount": "7753", "confirmedIncr": "2000", "deadIncr": "152", "deadCount": "288", "curedIncr": "0", "curedCount": "571"}, {"id": "1401", "dateId": "20200317", "confirmedCount": "9191", "confirmedIncr": "1438", "deadIncr": "21", "deadCount": "309", "curedIncr": "457", "curedCount": "1028"}, {"id": "1402", "dateId": "20200318", "confirmedCount": "11178", "confirmedIncr": "1987", "deadIncr": "182", "deadCount": "491", "curedIncr": "53", "curedCount": "1081"}, {"id": "1403", "dateId": "20200319", "confirmedCount": "17147", "confirmedIncr": "5969", "deadIncr": "276", "deadCount": "767", "curedIncr": "0", "curedCount": "1081"}, {"id": "1404", "dateId": "20200320", "confirmedCount": "19980", "confirmedIncr": "2833", "deadIncr": "235", "deadCount": "1002", "curedIncr": "507", "curedCount": "1588"}, {"id": "1405", "dateId": "20200321", "confirmedCount": "24926", "confirmedIncr": "4946", "deadIncr": "324", "deadCount": "1326", "curedIncr": "537", "curedCount": "2125"}, {"id": "1406", "dateId": "20200322", "confirmedCount": "28572", "confirmedIncr": "3646", "deadIncr": "394", "deadCount": "1720", "curedIncr": "450", "curedCount": "2575"}, {"id": "1407", "dateId": "20200323", "confirmedCount": "33089", "confirmedIncr": "4517", "deadIncr": "462", "deadCount": "2182", "curedIncr": "780", "curedCount": "3355"}, {"id": "1408", "dateId": "20200324", "confirmedCount": "42058", "confirmedIncr": "8969", "deadIncr": "809", "deadCount": "2991", "curedIncr": "439", "curedCount": "3794"}, {"id": "1409", "dateId": "20200325", "confirmedCount": "47610", "confirmedIncr": "5552", "deadIncr": "443", "deadCount": "3434", "curedIncr": "1573", "curedCount": "5367"}, {"id": "1410", "dateId": "20200326", "confirmedCount": "56188", "confirmedIncr": "8578", "deadIncr": "655", "deadCount": "4089", "curedIncr": "1648", "curedCount": "7015"}, {"id": "1411", "dateId": "20200327", "confirmedCount": "64059", "confirmedIncr": "7871", "deadIncr": "769", "deadCount": "4858", "curedIncr": "0", "curedCount": "7015"}, {"id": "1412", "dateId": "20200328", "confirmedCount": "72248", "confirmedIncr": "8189", "deadIncr": "832", "deadCount": "5690", "curedIncr": "5270", "curedCount": "12285"}, {"id": "1413", "dateId": "20200329", "confirmedCount": "78797", "confirmedIncr": "6549", "deadIncr": "838", "deadCount": "6528", "curedIncr": "0", "curedCount": "12285"}, {"id": "1414", "dateId": "20200330", "confirmedCount": "85195", "confirmedIncr": "6398", "deadIncr": "812", "deadCount": "7340", "curedIncr": "2424", "curedCount": "14709"}, {"id": "1415", "dateId": "20200331", "confirmedCount": "94417", "confirmedIncr": "9222", "deadIncr": "849", "deadCount": "8189", "curedIncr": "0", "curedCount": "14709"}, {"id": "1416", "dateId": "20200401", "confirmedCount": "102136", "confirmedIncr": "7719", "deadIncr": "864", "deadCount": "9053", "curedIncr": "7938", "curedCount": "22647"}, {"id": "1417", "dateId": "20200402", "confirmedCount": "110238", "confirmedIncr": "8102", "deadIncr": "950", "deadCount": "10003", "curedIncr": "4096", "curedCount": "26743"}, {"id": "1418", "dateId": "20200403", "confirmedCount": "117710", "confirmedIncr": "7472", "deadIncr": "932", "deadCount": "10935", "curedIncr": "3770", "curedCount": "30513"}, {"id": "1419", "dateId": "20200404", "confirmedCount": "124736", "confirmedIncr": "7026", "deadIncr": "809", "deadCount": "11744", "curedIncr": "3706", "curedCount": "34219"}, {"id": "1420", "dateId": "20200405", "confirmedCount": "130759", "confirmedIncr": "6023", "deadIncr": "674", "deadCount": "12418", "curedIncr": "3861", "curedCount": "38080"}, {"id": "1421", "dateId": "20200406", "confirmedCount": "135032", "confirmedIncr": "4273", "deadIncr": "637", "deadCount": "13055", "curedIncr": "0", "curedCount": "38080"}, {"id": "1422", "dateId": "20200407", "confirmedCount": "140510", "confirmedIncr": "5478", "deadIncr": "743", "deadCount": "13798", "curedIncr": "5128", "curedCount": "43208"}, {"id": "1423", "dateId": "20200408", "confirmedCount": "146690", "confirmedIncr": "6180", "deadIncr": "757", "deadCount": "14555", "curedIncr": "4813", "curedCount": "48021"}, {"id": "1424", "dateId": "20200409", "confirmedCount": "152446", "confirmedIncr": "5756", "deadIncr": "683", "deadCount": "15238", "curedIncr": "4144", "curedCount": "52165"}, {"id": "1425", "dateId": "20200410", "confirmedCount": "157022", "confirmedIncr": "4576", "deadIncr": "605", "deadCount": "15843", "curedIncr": "3503", "curedCount": "55668"}, {"id": "1426", "dateId": "20200411", "confirmedCount": "161852", "confirmedIncr": "4830", "deadIncr": "510", "deadCount": "16353", "curedIncr": "3441", "curedCount": "59109"}, {"id": "1427", "dateId": "20200412", "confirmedCount": "166019", "confirmedIncr": "4167", "deadIncr": "619", "deadCount": "16972", "curedIncr": "3282", "curedCount": "62391"}, {"id": "1428", "dateId": "20200413", "confirmedCount": "169496", "confirmedIncr": "3477", "deadIncr": "517", "deadCount": "17489", "curedIncr": "2336", "curedCount": "64727"}, {"id": "1429", "dateId": "20200414", "confirmedCount": "172541", "confirmedIncr": "3045", "deadIncr": "567", "deadCount": "18056", "curedIncr": "2777", "curedCount": "67504"}, {"id": "1430", "dateId": "20200415", "confirmedCount": "177633", "confirmedIncr": "5092", "deadIncr": "523", "deadCount": "18579", "curedIncr": "3349", "curedCount": "70853"}, {"id": "1431", "dateId": "20200416", "confirmedCount": "182816", "confirmedIncr": "5183", "deadIncr": "551", "deadCount": "19130", "curedIncr": "3944", "curedCount": "74797"}, {"id": "1432", "dateId": "20200417", "confirmedCount": "188068", "confirmedIncr": "5252", "deadIncr": "348", "deadCount": "19478", "curedIncr": "0", "curedCount": "74797"}, {"id": "1433", "dateId": "20200418", "confirmedCount": "191726", "confirmedIncr": "3658", "deadIncr": "565", "deadCount": "20043", "curedIncr": "-135", "curedCount": "74662"}, {"id": "1434", "dateId": "20200419", "confirmedCount": "195944", "confirmedIncr": "4218", "deadIncr": "410", "deadCount": "20453", "curedIncr": "2695", "curedCount": "77357"}, {"id": "1435", "dateId": "20200420", "confirmedCount": "200210", "confirmedIncr": "4266", "deadIncr": "399", "deadCount": "20852", "curedIncr": "3230", "curedCount": "80587"}, {"id": "1436", "dateId": "20200421", "confirmedCount": "204178", "confirmedIncr": "3968", "deadIncr": "430", "deadCount": "21282", "curedIncr": "1927", "curedCount": "82514"}, {"id": "1437", "dateId": "20200422", "confirmedCount": "208389", "confirmedIncr": "4211", "deadIncr": "435", "deadCount": "21717", "curedIncr": "3401", "curedCount": "85915"}, {"id": "1438", "dateId": "20200423", "confirmedCount": "213024", "confirmedIncr": "4635", "deadIncr": "440", "deadCount": "22157", "curedIncr": "3335", "curedCount": "89250"}, {"id": "1439", "dateId": "20200424", "confirmedCount": "219764", "confirmedIncr": "6740", "deadIncr": "367", "deadCount": "22524", "curedIncr": "3105", "curedCount": "92355"}, {"id": "1440", "dateId": "20200425", "confirmedCount": "223759", "confirmedIncr": "3995", "deadIncr": "378", "deadCount": "22902", "curedIncr": "3353", "curedCount": "95708"}, {"id": "1441", "dateId": "20200426", "confirmedCount": "207634", "confirmedIncr": "-16125", "deadIncr": "288", "deadCount": "23190", "curedIncr": "3024", "curedCount": "98732"}, {"id": "1442", "dateId": "20200427", "confirmedCount": "209465", "confirmedIncr": "1831", "deadIncr": "331", "deadCount": "23521", "curedIncr": "2143", "curedCount": "100875"}, {"id": "1443", "dateId": "20200428", "confirmedCount": "210773", "confirmedIncr": "1308", "deadIncr": "301", "deadCount": "23822", "curedIncr": "1673", "curedCount": "102548"}, {"id": "1444", "dateId": "20200429", "confirmedCount": "212917", "confirmedIncr": "2144", "deadIncr": "453", "deadCount": "24275", "curedIncr": "6399", "curedCount": "108947"}, {"id": "1445", "dateId": "20200430", "confirmedCount": "213435", "confirmedIncr": "518", "deadIncr": "268", "deadCount": "24543", "curedIncr": "3103", "curedCount": "112050"}, {"id": "1446", "dateId": "20200501", "confirmedCount": "215216", "confirmedIncr": "1781", "deadIncr": "281", "deadCount": "24824", "curedIncr": "2628", "curedCount": "114678"}, {"id": "1447", "dateId": "20200502", "confirmedCount": "216582", "confirmedIncr": "1366", "deadIncr": "276", "deadCount": "25100", "curedIncr": "2570", "curedCount": "117248"}, {"id": "1448", "dateId": "20200503", "confirmedCount": "217466", "confirmedIncr": "884", "deadIncr": "164", "deadCount": "25264", "curedIncr": "1654", "curedCount": "118902"}, {"id": "1449", "dateId": "20200504", "confirmedCount": "218011", "confirmedIncr": "545", "deadIncr": "164", "deadCount": "25428", "curedIncr": "2441", "curedCount": "121343"}, {"id": "1450", "dateId": "20200505", "confirmedCount": "219329", "confirmedIncr": "1318", "deadIncr": "185", "deadCount": "25613", "curedIncr": "2143", "curedCount": "123486"}, {"id": "1451", "dateId": "20200506", "confirmedCount": "220325", "confirmedIncr": "996", "deadIncr": "244", "deadCount": "25857", "curedIncr": "2516", "curedCount": "126002"}, {"id": "1452", "dateId": "20200507", "confirmedCount": "221447", "confirmedIncr": "1122", "deadIncr": "213", "deadCount": "26070", "curedIncr": "2509", "curedCount": "128511"}, {"id": "1453", "dateId": "20200508", "confirmedCount": "222857", "confirmedIncr": "1410", "deadIncr": "181", "deadCount": "26251", "curedIncr": "2332", "curedCount": "130843"}, {"id": "1454", "dateId": "20200509", "confirmedCount": "223578", "confirmedIncr": "721", "deadIncr": "227", "deadCount": "26478", "curedIncr": "3109", "curedCount": "133952"}, {"id": "1455", "dateId": "20200510", "confirmedCount": "224390", "confirmedIncr": "812", "deadIncr": "143", "deadCount": "26621", "curedIncr": "2214", "curedCount": "136166"}, {"id": "1456", "dateId": "20200511", "confirmedCount": "227436", "confirmedIncr": "3046", "deadIncr": "123", "deadCount": "26744", "curedIncr": "973", "curedCount": "137139"}, {"id": "1457", "dateId": "20200512", "confirmedCount": "228030", "confirmedIncr": "594", "deadIncr": "176", "deadCount": "26920", "curedIncr": "1841", "curedCount": "138980"}, {"id": "1458", "dateId": "20200513", "confirmedCount": "228691", "confirmedIncr": "661", "deadIncr": "184", "deadCount": "27104", "curedIncr": "1843", "curedCount": "140823"}, {"id": "1459", "dateId": "20200514", "confirmedCount": "229540", "confirmedIncr": "849", "deadIncr": "217", "deadCount": "27321", "curedIncr": "2551", "curedCount": "143374"}, {"id": "1460", "dateId": "20200515", "confirmedCount": "230183", "confirmedIncr": "643", "deadIncr": "138", "deadCount": "27459", "curedIncr": "1409", "curedCount": "144783"}, {"id": "1461", "dateId": "20200516", "confirmedCount": "230698", "confirmedIncr": "515", "deadIncr": "104", "deadCount": "27563", "curedIncr": "0", "curedCount": "144783"}, {"id": "1462", "dateId": "20200517", "confirmedCount": "231350", "confirmedIncr": "652", "deadIncr": "87", "deadCount": "27650", "curedIncr": "4793", "curedCount": "149576"}, {"id": "1463", "dateId": "20200518", "confirmedCount": "231606", "confirmedIncr": "256", "deadIncr": "59", "deadCount": "27709", "curedIncr": "800", "curedCount": "150376"}, {"id": "1464", "dateId": "20200519", "confirmedCount": "232037", "confirmedIncr": "431", "deadIncr": "69", "deadCount": "27778", "curedIncr": "0", "curedCount": "150376"}, {"id": "1465", "dateId": "20200520", "confirmedCount": "232555", "confirmedIncr": "518", "deadIncr": "110", "deadCount": "27888", "curedIncr": "0", "curedCount": "150376"}, {"id": "1466", "dateId": "20200521", "confirmedCount": "233037", "confirmedIncr": "482", "deadIncr": "52", "deadCount": "27940", "curedIncr": "0", "curedCount": "150376"}, {"id": "1467", "dateId": "20200522", "confirmedCount": "234824", "confirmedIncr": "1787", "deadIncr": "688", "deadCount": "28628", "curedIncr": "918", "curedCount": "151294"}, {"id": "1468", "dateId": "20200523", "confirmedCount": "235290", "confirmedIncr": "466", "deadIncr": "50", "deadCount": "28678", "curedIncr": "0", "curedCount": "151294"}, {"id": "1469", "dateId": "20200524", "confirmedCount": "235772", "confirmedIncr": "482", "deadIncr": "74", "deadCount": "28752", "curedIncr": "0", "curedCount": "151294"}, {"id": "1470", "dateId": "20200525", "confirmedCount": "235400", "confirmedIncr": "-372", "deadIncr": "-1918", "deadCount": "26834", "curedIncr": "-918", "curedCount": "150376"}, {"id": "1471", "dateId": "20200526", "confirmedCount": "236259", "confirmedIncr": "859", "deadIncr": "283", "deadCount": "27117", "curedIncr": "0", "curedCount": "150376"}, {"id": "1472", "dateId": "20200527", "confirmedCount": "236769", "confirmedIncr": "510", "deadIncr": "1", "deadCount": "27118", "curedIncr": "0", "curedCount": "150376"}, {"id": "1473", "dateId": "20200528", "confirmedCount": "237906", "confirmedIncr": "1137", "deadIncr": "1", "deadCount": "27119", "curedIncr": "0", "curedCount": "150376"}, {"id": "1474", "dateId": "20200529", "confirmedCount": "238564", "confirmedIncr": "658", "deadIncr": "2", "deadCount": "27121", "curedIncr": "0", "curedCount": "150376"}, {"id": "1475", "dateId": "20200530", "confirmedCount": "239228", "confirmedIncr": "664", "deadIncr": "4", "deadCount": "27125", "curedIncr": "0", "curedCount": "150376"}, {"id": "1476", "dateId": "20200531", "confirmedCount": "239600", "confirmedIncr": "372", "deadIncr": "1918", "deadCount": "29043", "curedIncr": "0", "curedCount": "150376"}, {"id": "1477", "dateId": "20200601", "confirmedCount": "239638", "confirmedIncr": "38", "deadIncr": "-1916", "deadCount": "27127", "curedIncr": "0", "curedCount": "150376"}, {"id": "1478", "dateId": "20200602", "confirmedCount": "239932", "confirmedIncr": "294", "deadIncr": "0", "deadCount": "27127", "curedIncr": "0", "curedCount": "150376"}, {"id": "1479", "dateId": "20200603", "confirmedCount": "240326", "confirmedIncr": "394", "deadIncr": "1", "deadCount": "27128", "curedIncr": "0", "curedCount": "150376"}, {"id": "1480", "dateId": "20200604", "confirmedCount": "240660", "confirmedIncr": "334", "deadIncr": "5", "deadCount": "27133", "curedIncr": "0", "curedCount": "150376"}, {"id": "1481", "dateId": "20200605", "confirmedCount": "240978", "confirmedIncr": "318", "deadIncr": "1", "deadCount": "27134", "curedIncr": "0", "curedCount": "150376"}, {"id": "1482", "dateId": "20200606", "confirmedCount": "241310", "confirmedIncr": "332", "deadIncr": "1", "deadCount": "27135", "curedIncr": "0", "curedCount": "150376"}, {"id": "1483", "dateId": "20200607", "confirmedCount": "241550", "confirmedIncr": "240", "deadIncr": "1", "deadCount": "27136", "curedIncr": "0", "curedCount": "150376"}, {"id": "1484", "dateId": "20200608", "confirmedCount": "241717", "confirmedIncr": "167", "deadIncr": "0", "deadCount": "27136", "curedIncr": "0", "curedCount": "150376"}, {"id": "1485", "dateId": "20200609", "confirmedCount": "241966", "confirmedIncr": "249", "deadIncr": "0", "deadCount": "27136", "curedIncr": "0", "curedCount": "150376"}, {"id": "1486", "dateId": "20200610", "confirmedCount": "242280", "confirmedIncr": "314", "deadIncr": "0", "deadCount": "27136", "curedIncr": "0", "curedCount": "150376"}, {"id": "1487", "dateId": "20200611", "confirmedCount": "242707", "confirmedIncr": "427", "deadIncr": "0", "deadCount": "27136", "curedIncr": "0", "curedCount": "150376"}, {"id": "1488", "dateId": "20200612", "confirmedCount": "243209", "confirmedIncr": "502", "deadIncr": "0", "deadCount": "27136", "curedIncr": "0", "curedCount": "150376"}, {"id": "1489", "dateId": "20200613", "confirmedCount": "243605", "confirmedIncr": "396", "deadIncr": "0", "deadCount": "27136", "curedIncr": "0", "curedCount": "150376"}, {"id": "1490", "dateId": "20200614", "confirmedCount": "243928", "confirmedIncr": "323", "deadIncr": "0", "deadCount": "27136", "curedIncr": "0", "curedCount": "150376"}, {"id": "1491", "dateId": "20200615", "confirmedCount": "244109", "confirmedIncr": "181", "deadIncr": "0", "deadCount": "27136", "curedIncr": "0", "curedCount": "150376"}, {"id": "1492", "dateId": "20200616", "confirmedCount": "244328", "confirmedIncr": "219", "deadIncr": "0", "deadCount": "27136", "curedIncr": "0", "curedCount": "150376"}, {"id": "1493", "dateId": "20200617", "confirmedCount": "244683", "confirmedIncr": "355", "deadIncr": "0", "deadCount": "27136", "curedIncr": "0", "curedCount": "150376"}, {"id": "1494", "dateId": "20200618", "confirmedCount": "245268", "confirmedIncr": "585", "deadIncr": "0", "deadCount": "27136", "curedIncr": "0", "curedCount": "150376"}, {"id": "1495", "dateId": "20200619", "confirmedCount": "245575", "confirmedIncr": "307", "deadIncr": "1179", "deadCount": "28315", "curedIncr": "0", "curedCount": "150376"}, {"id": "1496", "dateId": "20200620", "confirmedCount": "245938", "confirmedIncr": "363", "deadIncr": "7", "deadCount": "28322", "curedIncr": "0", "curedCount": "150376"}, {"id": "1497", "dateId": "20200621", "confirmedCount": "246272", "confirmedIncr": "334", "deadIncr": "1", "deadCount": "28323", "curedIncr": "0", "curedCount": "150376"}, {"id": "1498", "dateId": "20200622", "confirmedCount": "246504", "confirmedIncr": "232", "deadIncr": "1", "deadCount": "28324", "curedIncr": "0", "curedCount": "150376"}, {"id": "1499", "dateId": "20200623", "confirmedCount": "246752", "confirmedIncr": "248", "deadIncr": "1", "deadCount": "28325", "curedIncr": "0", "curedCount": "150376"}, {"id": "1500", "dateId": "20200624", "confirmedCount": "247086", "confirmedIncr": "334", "deadIncr": "2", "deadCount": "28327", "curedIncr": "0", "curedCount": "150376"}, {"id": "1501", "dateId": "20200625", "confirmedCount": "247486", "confirmedIncr": "400", "deadIncr": "3", "deadCount": "28330", "curedIncr": "0", "curedCount": "150376"}, {"id": "1502", "dateId": "20200626", "confirmedCount": "247905", "confirmedIncr": "419", "deadIncr": "8", "deadCount": "28338", "curedIncr": "0", "curedCount": "150376"}, {"id": "1503", "dateId": "20200627", "confirmedCount": "248469", "confirmedIncr": "564", "deadIncr": "3", "deadCount": "28341", "curedIncr": "0", "curedCount": "150376"}, {"id": "1504", "dateId": "20200628", "confirmedCount": "248770", "confirmedIncr": "301", "deadIncr": "2", "deadCount": "28343", "curedIncr": "0", "curedCount": "150376"}, {"id": "1505", "dateId": "20200629", "confirmedCount": "248970", "confirmedIncr": "200", "deadIncr": "3", "deadCount": "28346", "curedIncr": "0", "curedCount": "150376"}, {"id": "1506", "dateId": "20200630", "confirmedCount": "249271", "confirmedIncr": "301", "deadIncr": "9", "deadCount": "28355", "curedIncr": "0", "curedCount": "150376"}, {"id": "1507", "dateId": "20200701", "confirmedCount": "249659", "confirmedIncr": "388", "deadIncr": "8", "deadCount": "28363", "curedIncr": "0", "curedCount": "150376"}, {"id": "1508", "dateId": "20200702", "confirmedCount": "250103", "confirmedIncr": "444", "deadIncr": "5", "deadCount": "28368", "curedIncr": "0", "curedCount": "150376"}]